WtFileUtils/BitStream.py
WtFileUtils/BitStream.pyi
WtFileUtils/Exceptions.py
WtFileUtils/__init__.py
WtFileUtils/writeStream.py
WtFileUtils/FileSystem/FSDirectory.py
WtFileUtils/FileSystem/File.py
WtFileUtils/FileSystem/FileSystemQuery.py
WtFileUtils/FileSystem/Filesystem.py
WtFileUtils/FileSystem/__init__.py
WtFileUtils/blk/BlkParser.py
WtFileUtils/blk/Block.py
WtFileUtils/blk/Chunk.py
WtFileUtils/blk/FileInfo.py
WtFileUtils/blk/ParamParser.py
WtFileUtils/blk/TypeParsedDEP.py
WtFileUtils/blk/__init__.py
WtFileUtils/vromfs/FileInfoUtils.py
WtFileUtils/vromfs/VROMFs.py
WtFileUtils/vromfs/VROMFsCollection.py
WtFileUtils/vromfs/__init__.py
WtFileUtils/vromfs/metadata.py
wtfileutils-0.1.5.dist-info/METADATA
wtfileutils-0.1.5.dist-info/WHEEL
wtfileutils-0.1.5.dist-info/licenses/LICENSE
wtfileutils-0.1.5.dist-info/RECORD
