Metadata-Version: 2.4
Name: WtFileUtils
Version: 0.1.5
Summary: A VROMFs and Binary BLK Reader
Project-URL: Homepage, https://github.com/LivingTheDagor/WtFileUtils
Author-email: LivingTheDagor <LivingTheDagor@gmail.com>
License-File: LICENSE
Classifier: License :: OSI Approved :: MIT License
Classifier: Operating System :: OS Independent
Classifier: Programming Language :: Python :: 3
Requires-Python: >=3.12
